stratix_summarizer/__init__.py
stratix_summarizer/main.py
stratix_summarizer/prompts.py
stratix_summarizer-2025.12.21162741.dist-info/METADATA
stratix_summarizer-2025.12.21162741.dist-info/WHEEL
stratix_summarizer-2025.12.21162741.dist-info/top_level.txt
stratix_summarizer-2025.12.21162741.dist-info/RECORD
