Metadata-Version: 2.4
Name: stratix-summarizer
Version: 2025.12.21162741
Summary: A new package is designed to analyze and summarize business strategy narratives, investor communications, or crowdfunding campaign descriptions to extract structured insights about startup funding act
Author-email: stratix-summarizer <hi@eugene.plus>
License: MIT
Project-URL: Homepage, https://github.com/chigwell/stratix-summarizer
Requires-Python: >=3.9
Requires-Dist: langchain-llm7>=0.0.0
Requires-Dist: llmatch-messages>=0.0.0
Requires-Dist: langchain-core>=0.3.0
